{"n":94,"name":"الشرح","phonetic":"Ash-Sharh","fr":"L'ouverture","type":"meccan","verses":[["أَلَمۡ نَشۡرَحۡ لَكَ صَدۡرَكَ","N'avons-Nous pas ouvert pour toi ta poitrine","Alam nashrah laka sadraka"],["وَوَضَعۡنَا عَنكَ وِزۡرَكَ","Et ne t'avons-Nous pas déchargé du fardeau","WawadaAAna AAanka wizraka"],["ٱلَّذِيٓ أَنقَضَ ظَهۡرَكَ","qui accablait ton dos","Allathee anqada thahraka"],["وَرَفَعۡنَا لَكَ ذِكۡرَكَ","Et exalté pour toi ta renommée","WarafaAAna laka thikraka"],["فَإِنَّ مَعَ ٱلۡعُسۡرِ يُسۡرًا","A côté de la difficulté est, certes, une facilité","Fainna maAAa alAAusri yusran"],["إِنَّ مَعَ ٱلۡعُسۡرِ يُسۡرٗا","A côté de la difficulté est, certes, une facilité","Inna maAAa alAAusri yusran"],["فَإِذَا فَرَغۡتَ فَٱنصَبۡ","Quand tu te libères, donc, lève-toi","Faitha faraghta fainsab"],["وَإِلَىٰ رَبِّكَ فَٱرۡغَب","et à ton Seigneur aspire","Waila rabbika fairghab"]]}